evsemaster/__init__.py
evsemaster/data_types.py
evsemaster/evse_protocol.py
evsemaster-1.3.2.dist-info/LICENSE
evsemaster-1.3.2.dist-info/METADATA
evsemaster-1.3.2.dist-info/WHEEL
evsemaster-1.3.2.dist-info/RECORD
