Metadata-Version: 2.1
Name: evsemaster
Version: 1.3.2
Summary: Python implementation of the EVSEMaster App
License: MIT
Author: Rafaël Schridi
Author-email: rafael@schridi.nl
Requires-Python: >=3.13
Classifier: License :: OSI Approved :: MIT License
Classifier: Programming Language :: Python :: 3
Requires-Dist: pydantic (>=2.10.0,<3.0.0)
Requires-Dist: tzdata (>=2025.1,<2026.0)
